pysnowball/__init__.py
pysnowball/api_ref.py
pysnowball/bond.py
pysnowball/capital.py
pysnowball/cons.py
pysnowball/cube.py
pysnowball/f10.py
pysnowball/finance.py
pysnowball/fund.py
pysnowball/hkex.py
pysnowball/index.py
pysnowball/realtime.py
pysnowball/report.py
pysnowball/scan.py
pysnowball/token.py
pysnowball/user.py
pysnowball/utls.py
tests/__init__.py
tests/test_fund.py
tests/test_scan.py
ipysnowball-1.0.5.dist-info/LICENSE
ipysnowball-1.0.5.dist-info/METADATA
ipysnowball-1.0.5.dist-info/WHEEL
ipysnowball-1.0.5.dist-info/top_level.txt
ipysnowball-1.0.5.dist-info/RECORD
