Metadata-Version: 2.1
Name: ipysnowball
Version: 1.0.5
Summary: 原版雪球Python API pysnowball 的修改
Home-page: https://github.com/issaTan/pysnowball
Author: IssaTan
Author-email: tanxinhao.1990@gmail.com
Keywords: Financial Data,XueQiu,Snow Ball,雪球,Python Api
Classifier: Programming Language :: Python :: 3
Classifier: License :: OSI Approved :: MIT License
Classifier: Operating System :: OS Independent
License-File: LICENSE
Requires-Dist: requests (>=2.18.4)
Requires-Dist: beautifulsoup4 (>=4.10.0)
